{"cameraMode":{"drawMode":0,"name":"Shaded","section":"Shading Mode"},"sceneLighting":true,"audioPlay":false,"sceneViewState":{"m_AlwaysRefresh":false,"showFog":true,"showSkybox":true,"showFlares":true,"showImageEffects":true,"showParticleSystems":true,"showVisualEffectGraphs":true,"m_FxEnabled":true},"in2DMode":false,"pivot":{"x":125.36833953857422,"y":-17.942699432373048,"z":29.496570587158204},"rotation":{"x":0.45836785435676577,"y":-0.05177892744541168,"z":0.026572823524475099,"w":0.8869086503982544},"size":40.28558349609375,"orthographic":false}