{"cameraMode":{"drawMode":0,"name":"Shaded","section":"Shading Mode"},"sceneLighting":true,"audioPlay":false,"sceneViewState":{"m_AlwaysRefresh":false,"showFog":true,"showSkybox":true,"showFlares":true,"showImageEffects":true,"showParticleSystems":true,"showVisualEffectGraphs":true,"m_FxEnabled":true},"in2DMode":false,"pivot":{"x":4.216395378112793,"y":18.812410354614259,"z":29.07564926147461},"rotation":{"x":-0.10771096497774124,"y":-0.24289044737815858,"z":0.027151210233569146,"w":-0.9636783599853516},"size":57.581600189208987,"orthographic":false}